Lab2/fsm-assignments/problem4_link/slave_fsm.v
// slave_fsm.v
// Implements the slave side of the req/ack handshake.
// It latches data and asserts ack for exactly 2 cycles.
module slave_fsm(
    input wire        clk,
    input wire        rst,       // sync active-high
    input wire        req,
    input wire  [7:0] data_in,
    output wire       ack,
    output reg  [7:0] last_byte  // observable for TB
);

    // State encoding
    localparam S_IDLE        = 2'd0;
    localparam S_LATCH_ACK   = 2'd1;
    localparam S_HOLD_ACK    = 2'd2;
    localparam S_WAIT_NO_REQ = 2'd3;
    
    // Registers
    reg [1:0] state_reg, state_next;

    // Sequential logic for state and data latching
    always @(posedge clk) begin
        if (rst) begin
            state_reg <= S_IDLE;
            last_byte <= 8'h00;
        end else begin
            state_reg <= state_next;
            // Latch data only when transitioning to S_LATCH_ACK
            if (state_next == S_LATCH_ACK) begin
                last_byte <= data_in;
            end
        end
    end

    // Next-state combinational logic
    always @(*) begin
        state_next = state_reg;
        case (state_reg)
            S_IDLE: begin
                if (req) begin
                    state_next = S_LATCH_ACK;
                end
            end
            
            S_LATCH_ACK: begin
                // First cycle of ack, hold for one more
                state_next = S_HOLD_ACK;
            end

            S_HOLD_ACK: begin
                // Second cycle of ack done, wait for req to drop
                state_next = S_WAIT_NO_REQ;
            end

            S_WAIT_NO_REQ: begin
                if (!req) begin
                    // Master has seen ack, return to idle
                    state_next = S_IDLE;
                end
            end
            
            default: begin
                state_next = S_IDLE;
            end
        endcase
    end
    
    // Output logic for ack
    assign ack = (state_reg == S_LATCH_ACK) || (state_reg == S_HOLD_ACK) || (state_reg == S_WAIT_NO_REQ);

endmodule

Lab2/fsm-assignments/problem4_link/master_fsm.v
// master_fsm.v
// Implements the master side of the req/ack handshake protocol.
// It sends a burst of 4 bytes of data.
module master_fsm(
    input wire       clk,
    input wire       rst, // sync active-high
    input wire       ack,
    output wire      req,
    output wire [7:0] data,
    output wire      done // 1-cycle when burst completes
);

    // State encoding
    localparam S_IDLE        = 3'd0;
    localparam S_DRIVE_DATA  = 3'd1;
    localparam S_WAIT_ACK    = 3'd2;
    localparam S_WAIT_NO_ACK = 3'd3;
    localparam S_DONE        = 3'd4;

    // Registers
    reg [2:0] state_reg, state_next;
    reg [1:0] byte_count_reg, byte_count_next;
    reg [7:0] data_reg;

    // Sequential logic for state and byte counter
    always @(posedge clk) begin
        if (rst) begin
            state_reg      <= S_IDLE;
            byte_count_reg <= 2'd0;
        end else begin
            state_reg      <= state_next;
            byte_count_reg <= byte_count_next;
        end
    end

    // Example data to send (A0, A1, A2, A3)
    assign data = data_reg;

    // Next-state and output combinational logic
    always @(*) begin
        // Default assignments
        state_next      = state_reg;
        byte_count_next = byte_count_reg;
        data_reg        = 8'hA0 + byte_count_reg; // Default data
        
        case (state_reg)
            S_IDLE: begin
                // Start the transfer
                state_next = S_DRIVE_DATA;
            end
            
            S_DRIVE_DATA: begin
                // Move to wait for slave's acknowledgement
                state_next = S_WAIT_ACK;
            end

            S_WAIT_ACK: begin
                if (ack) begin
                    // Slave acknowledged, check if we are done
                    if (byte_count_reg == 2'd3) begin
                        state_next = S_DONE;
                    end else begin
                        state_next      = S_WAIT_NO_ACK;
                        byte_count_next = byte_count_reg + 1;
                    end
                end
            end

            S_WAIT_NO_ACK: begin
                if (!ack) begin
                    // Handshake complete for this byte, start next one
                    state_next = S_DRIVE_DATA;
                end
            end

            S_DONE: begin
                // Pulse done for one cycle and return to idle
                state_next = S_IDLE;
            end
            
            default: begin
                state_next = S_IDLE;
            end
        endcase
    end

    // Output logic
    assign req  = (state_reg == S_DRIVE_DATA) || (state_reg == S_WAIT_ACK);
    assign done = (state_reg == S_DONE);

endmodule

Lab2/fsm-assignments/problem4_link/link_top.v
// link_top.v
// Top-level module connecting the master and slave FSMs.
module link_top(
    input wire  clk,
    input wire  rst,
    output wire done
);
    // Internal wires for handshake
    wire        req;
    wire        ack;
    wire [7:0]  data;

    // Instantiate master FSM
    master_fsm u_master (
        .clk(clk),
        .rst(rst),
        .ack(ack),
        .req(req),
        .data(data),
        .done(done)
    );

    // Instantiate slave FSM
    slave_fsm u_slave (
        .clk(clk),
        .rst(rst),
        .req(req),
        .data_in(data),
        .ack(ack),
        .last_byte() // Not used in top, but observable in TB
    );

endmodule

Lab2/fsm-assignments/problem4_link/tb_link_top.v
// tb_link_top.v
// Testbench for the master-slave link.
module tb_link_top;
    reg clk;
    reg rst;
    wire done;

    // Instantiate the design under test (DUT)
    link_top dut (
        .clk(clk),
        .rst(rst),
        .done(done)
    );

    // 1. Clock generation (100 MHz clock, 10 ns period)
    initial begin
        clk = 0;
        forever #5 clk = ~clk;
    end

    // 2. Test sequence
    initial begin
        // Setup waveform dumping
        $dumpfile("handshake_waves.vcd");
        $dumpvars(0, tb_link_top);

        // Apply reset
        rst = 1;
        repeat(2) @(posedge clk);
        rst = 0;
        
        $display("Time\tReq\tAck\tData\tDone\tLastByte");
        
        // 3. Run until 'done' is high
        wait (done);
        
        @(posedge clk); // Let done pulse finish
        $display("INFO: 4-byte transfer complete. Simulation finished.");
        $finish;
    end
    
    // Monitor for logging key signals
    always @(posedge clk) begin
        if (!rst) begin
            $display("%0t\t%b\t%b\t%h\t%b\t%h",
                $time,
                dut.u_master.req,
                dut.u_slave.ack,
                dut.u_master.data,
                done,
                dut.u_slave.last_byte
            );
        end
    end

endmodule

Lab2/fsm-assignments/problem4_link/handshake_waves.vcd
$date
	Sun Aug 17 22:44:53 2025
$end
$version
	Icarus Verilog
$end
$timescale
	1s
$end
$scope module tb_link_top $end
$var wire 1 ! done $end
$var reg 1 " clk $end
$var reg 1 # rst $end
$scope module dut $end
$var wire 1 " clk $end
$var wire 1 # rst $end
$var wire 1 $ req $end
$var wire 1 ! done $end
$var wire 8 % data [7:0] $end
$var wire 1 & ack $end
$scope module u_master $end
$var wire 1 " clk $end
$var wire 8 ' data [7:0] $end
$var wire 1 $ req $end
$var wire 1 # rst $end
$var wire 1 ! done $end
$var wire 1 & ack $end
$var parameter 3 ( S_DONE $end
$var parameter 3 ) S_DRIVE_DATA $end
$var parameter 3 * S_IDLE $end
$var parameter 3 + S_WAIT_ACK $end
$var parameter 3 , S_WAIT_NO_ACK $end
$var reg 2 - byte_count_next [1:0] $end
$var reg 2 . byte_count_reg [1:0] $end
$var reg 8 / data_reg [7:0] $end
$var reg 3 0 state_next [2:0] $end
$var reg 3 1 state_reg [2:0] $end
$upscope $end
$scope module u_slave $end
$var wire 1 & ack $end
$var wire 1 " clk $end
$var wire 8 2 data_in [7:0] $end
$var wire 1 $ req $end
$var wire 1 # rst $end
$var parameter 2 3 S_HOLD_ACK $end
$var parameter 2 4 S_IDLE $end
$var parameter 2 5 S_LATCH_ACK $end
$var parameter 2 6 S_WAIT_NO_REQ $end
$var reg 8 7 last_byte [7:0] $end
$var reg 2 8 state_next [1:0] $end
$var reg 2 9 state_reg [1:0] $end
$upscope $end
$upscope $end
$upscope $end
$enddefinitions $end
$comment Show the parameter values. $end
$dumpall
b11 6
b1 5
b0 4
b10 3
b11 ,
b10 +
b0 *
b1 )
b100 (
$end
#0
$dumpvars
bx 9
bx 8
bx 7
bx 2
bx 1
bx 0
bx /
bx .
bx -
bx '
x&
bx %
x$
1#
0"
x!
$end
#5
0&
b10100000 %
b10100000 '
b10100000 2
b10100000 /
b0 -
b1 0
0$
b0 8
b0 .
0!
b0 1
b0 7
b0 9
1"
#10
0"
#15
0#
1"
#20
0"
#25
b1 8
b10 0
1$
b1 1
1"
#30
0"
#35
b1 -
b11 0
1&
b10 8
b10100000 7
b1 9
b10 1
1"
#40
0"
#45
b10100001 %
b10100001 '
b10100001 2
b10100001 /
0$
b11 8
b1 .
b11 1
b10 9
1"
#50
0"
#55
b0 8
b11 9
1"
#60
0"
#65
b1 0
0&
b0 9
1"
#70
0"
#75
b1 8
b10 0
1$
b1 1
1"
#80
0"
#85
b10 -
b11 0
1&
b10 8
b10 1
b10100001 7
b1 9
1"
#90
0"
#95
b11 8
b10100010 %
b10100010 '
b10100010 2
b10100010 /
0$
b10 9
b10 .
b11 1
1"
#100
0"
#105
b0 8
b11 9
1"
#110
0"
#115
b1 0
0&
b0 9
1"
#120
0"
#125
b1 8
b10 0
1$
b1 1
1"
#130
0"
#135
b11 -
b11 0
1&
b10 8
b10100010 7
b1 9
b10 1
1"
#140
0"
#145
b10100011 %
b10100011 '
b10100011 2
b10100011 /
0$
b11 8
b11 .
b11 1
b10 9
1"
#150
0"
#155
b0 8
b11 9
1"
#160
0"
#165
b1 0
0&
b0 9
1"
#170
0"
#175
b1 8
b10 0
1$
b1 1
1"
#180
0"
#185
b100 0
1&
b10 8
b10 1
b10100011 7
b1 9
1"
#190
0"
#195
b11 8
b0 0
0$
b10 9
1!
b100 1
1"
#200
0"
#205
b1 0
b0 8
0!
b0 1
b11 9
1"
