Lab2/fsm-assignments/problem3_vending/vending_mealy.v
// Vending Machine (Mealy FSM) — price = 20, coins = 5 and 10
module vending_mealy(
    input        clk,
    input        reset,      // active-high, synchronous
    input  [1:0] coin,       // 00=none, 01=5, 10=10, 11=ignored
    output wire  dispense,   // 1-cycle pulse when vend
    output wire  chg5        // 1-cycle pulse when vend + give 5 back
);

    // State encoding (represents running total)
    parameter S0  = 2'd0; // 0
    parameter S5  = 2'd1; // 5
    parameter S10 = 2'd2; // 10
    parameter S15 = 2'd3; // 15

    reg [1:0] state, next_state;

    // Coin decode
    wire coin5  = (coin == 2'b01);
    wire coin10 = (coin == 2'b10);
    wire noCoin = (coin == 2'b00);

    // State register
    always @(posedge clk or posedge reset) begin
        if (reset)
            state <= S0;
        else
            state <= next_state;
    end

    // Next state + output logic
    reg dispense_r, chg5_r;
    always @(*) begin
        // defaults
        next_state = state;
        dispense_r = 0;
        chg5_r     = 0;

        case (state)
            S0: begin
                if (coin5)       next_state = S5;
                else if (coin10) next_state = S10;
            end

            S5: begin
                if (coin5)       next_state = S10;
                else if (coin10) next_state = S15;
            end

            S10: begin
                if (coin5)       next_state = S15;
                else if (coin10) begin
                    dispense_r = 1;
                    next_state = S0;
                end
            end

            S15: begin
                if (coin5) begin
                    dispense_r = 1;
                    next_state = S0;
                end else if (coin10) begin
                    dispense_r = 1;
                    chg5_r     = 1;
                    next_state = S0;
                end
            end
        endcase

        if (noCoin) next_state = state; // stay if no coin
    end

    // Outputs as wires
    assign dispense = dispense_r;
    assign chg5     = chg5_r;

endmodule

Lab2/fsm-assignments/problem3_vending/tb_vending_mealy.v
`timescale 1ns/1ps
module tb_vending_mealy;
    reg clk, reset;
    reg [1:0] coin;
    wire dispense, chg5;

    vending_mealy dut (
        .clk(clk),
        .reset(reset),
        .coin(coin),
        .dispense(dispense),
        .chg5(chg5)
    );

    // clock generation
    initial begin
        clk = 0;
        forever #5 clk = ~clk; // 10 ns period
    end

    // helper tasks
    task put5;
    begin
        coin = 2'b01; @(posedge clk);
        coin = 2'b00; @(posedge clk);
    end
    endtask

    task put10;
    begin
        coin = 2'b10; @(posedge clk);
        coin = 2'b00; @(posedge clk);
    end
    endtask

    initial begin
        $dumpfile("dump.vcd");
        $dumpvars(0, tb_vending_mealy);

        coin = 2'b00;
        reset = 1; repeat(2) @(posedge clk);
        reset = 0; @(posedge clk);

        // 1) 10 + 10
        put10(); put10(); repeat(2) @(posedge clk);

        // 2) 5 + 5 + 10
        put5(); put5(); put10(); repeat(2) @(posedge clk);

        // 3) 10 + 5 + 10
        put10(); put5(); put10(); repeat(4) @(posedge clk);

        $finish;
    end
endmodule

Lab2/fsm-assignments/problem3_vending/dump.vcd
$date
	Sun Aug 17 20:15:38 2025
$end
$version
	Icarus Verilog
$end
$timescale
	1ps
$end
$scope module tb_vending_mealy $end
$var wire 1 ! dispense $end
$var wire 1 " chg5 $end
$var reg 1 # clk $end
$var reg 2 $ coin [1:0] $end
$var reg 1 % reset $end
$scope module dut $end
$var wire 1 " chg5 $end
$var wire 1 # clk $end
$var wire 2 & coin [1:0] $end
$var wire 1 ! dispense $end
$var wire 1 % reset $end
$var wire 1 ' noCoin $end
$var wire 1 ( coin5 $end
$var wire 1 ) coin10 $end
$var parameter 2 * S0 $end
$var parameter 2 + S10 $end
$var parameter 2 , S15 $end
$var parameter 2 - S5 $end
$var reg 1 . chg5_r $end
$var reg 1 / dispense_r $end
$var reg 2 0 next_state [1:0] $end
$var reg 2 1 state [1:0] $end
$upscope $end
$scope task put10 $end
$upscope $end
$scope task put5 $end
$upscope $end
$upscope $end
$enddefinitions $end
$comment Show the parameter values. $end
$dumpall
b1 -
b11 ,
b10 +
b0 *
$end
#0
$dumpvars
b0 1
b0 0
0/
0.
0)
0(
1'
b0 &
1%
b0 $
0#
0"
0!
$end
#5000
1#
#10000
0#
#15000
0%
1#
#20000
0#
#25000
b10 0
1)
0'
b10 $
b10 &
1#
#30000
0#
#35000
b10 1
b10 0
0)
1'
b0 $
b0 &
1#
#40000
0#
#45000
b0 0
1!
1/
1)
0'
b10 $
b10 &
1#
#50000
0#
#55000
b0 1
0!
0/
b0 0
0)
1'
b0 $
b0 &
1#
#60000
0#
#65000
1#
#70000
0#
#75000
1#
#80000
0#
#85000
b1 0
1(
0'
b1 $
b1 &
1#
#90000
0#
#95000
b1 1
b1 0
0(
1'
b0 $
b0 &
1#
#100000
0#
#105000
b10 0
1(
0'
b1 $
b1 &
1#
#110000
0#
#115000
b10 1
b10 0
0(
1'
b0 $
b0 &
1#
#120000
0#
#125000
b0 0
1!
1/
1)
0'
b10 $
b10 &
1#
#130000
0#
#135000
b0 1
0!
0/
b0 0
0)
1'
b0 $
b0 &
1#
#140000
0#
#145000
1#
#150000
0#
#155000
1#
#160000
0#
#165000
b10 0
1)
0'
b10 $
b10 &
1#
#170000
0#
#175000
b10 1
b10 0
0)
1'
b0 $
b0 &
1#
#180000
0#
#185000
b11 0
1(
0'
b1 $
b1 &
1#
#190000
0#
#195000
b11 1
b11 0
0(
1'
b0 $
b0 &
1#
#200000
0#
#205000
b0 0
1"
1.
1!
1/
1)
0'
b10 $
b10 &
1#
#210000
0#
#215000
b0 1
0"
0.
0!
0/
b0 0
0)
1'
b0 $
b0 &
1#
