Lab2/fsm-assignments/problem1_seqdet/seq_detect_mealy.v
module seq_detect_mealy(
    input clk, reset, x,
    output reg y
);
    reg [2:0] state, next_state;
    parameter S0=0, S1=1, S2=2, S3=3;

    always @(posedge clk or posedge reset) begin
        if (reset) state <= S0;
        else state <= next_state;
    end

    always @(*) begin
        y = 0;
        case (state)
            S0: if (x) next_state = S1; else next_state = S0;
            S1: if (x) next_state = S2; else next_state = S0;
            S2: if (~x) next_state = S3; else next_state = S2;
            S3: if (x) begin
                    next_state = S1; 
                    y = 1; // Mealy output
                end
                else next_state = S0;
        endcase
    end
endmodule

Lab2/fsm-assignments/problem1_seqdet/tb_seq_detect_mealy.v
`timescale 1ns/1ps
module tb_seq_detect_mealy;
    reg clk, reset, x;
    wire y;

    seq_detect_mealy dut(clk, reset, x, y);

    initial begin
        $dumpfile("dump.vcd");
        $dumpvars(0, tb_seq_detect_mealy);

        clk = 0;
        forever #5 clk = ~clk; // 10ns clock period
    end

    initial begin
        reset = 1; x = 0;
        #12 reset = 0;

        // Pattern: 11011011101
        #10 x=1; #10 x=1; #10 x=0; #10 x=1;
        #10 x=1; #10 x=0; #10 x=1; #10 x=1;
        #10 x=1; #10 x=0; #10 x=1;
        #20 $finish;
    end
endmodule

Lab2/fsm-assignments/problem1_seqdet/dump.vcd
$date
	Fri Aug 15 22:53:58 2025
$end
$version
	Icarus Verilog
$end
$timescale
	1ps
$end
$scope module tb_seq_detect_mealy $end
$var wire 1 ! y $end
$var reg 1 " clk $end
$var reg 1 # reset $end
$var reg 1 $ x $end
$scope module dut $end
$var wire 1 " clk $end
$var wire 1 # reset $end
$var wire 1 $ x $end
$var parameter 32 % S0 $end
$var parameter 32 & S1 $end
$var parameter 32 ' S2 $end
$var parameter 32 ( S3 $end
$var reg 3 ) next_state [2:0] $end
$var reg 3 * state [2:0] $end
$var reg 1 ! y $end
$upscope $end
$upscope $end
$enddefinitions $end
$comment Show the parameter values. $end
$dumpall
b11 (
b10 '
b1 &
b0 %
$end
#0
$dumpvars
b0 *
b0 )
0$
1#
0"
0!
$end
#5000
1"
#10000
0"
#12000
0#
#15000
1"
#20000
0"
#22000
b1 )
1$
#25000
b10 )
b1 *
1"
#30000
0"
#35000
b10 *
1"
#40000
0"
#42000
b11 )
0$
#45000
b0 )
b11 *
1"
#50000
0"
#52000
1!
b1 )
1$
#55000
b10 )
0!
b1 *
1"
#60000
0"
#65000
b10 *
1"
#70000
0"
#72000
b11 )
0$
#75000
b0 )
b11 *
1"
#80000
0"
#82000
1!
b1 )
1$
#85000
b10 )
0!
b1 *
1"
#90000
0"
#95000
b10 *
1"
#100000
0"
#105000
1"
#110000
0"
#112000
b11 )
0$
#115000
b0 )
b11 *
1"
#120000
0"
#122000
1!
b1 )
1$
#125000
b10 )
0!
b1 *
1"
#130000
0"
#135000
b10 *
1"
